gd_py_utils-0.0.8.dist-info/licenses/LICENSE
gdutils/__init__.py
gdutils/datacontainer/__init__.py
gdutils/datacontainer/container.py
gdutils/datacontainer/temp.py
gdutils/utils/__init__.py
gdutils/utils/decorators.py
gdutils/utils/io.py
gdutils/utils/logger.py
gdutils/utils/plotting.py
gdutils/utils/timer.py
gd_py_utils-0.0.8.dist-info/METADATA
gd_py_utils-0.0.8.dist-info/WHEEL
gd_py_utils-0.0.8.dist-info/top_level.txt
gd_py_utils-0.0.8.dist-info/RECORD
