Metadata-Version: 2.4
Name: gd-py-utils
Version: 0.0.8
Requires-Python: >=3.9
License-File: LICENSE
Requires-Dist: numpy
Requires-Dist: matplotlib
Provides-Extra: docs
Requires-Dist: mkdocs; extra == "docs"
Requires-Dist: mkdocs-material; extra == "docs"
Requires-Dist: mkdocs-mermaid2-plugin; extra == "docs"
Requires-Dist: mkdocs-snippets; extra == "docs"
Requires-Dist: mkdocs-exclude; extra == "docs"
Requires-Dist: mkdocstrings-python; extra == "docs"
Dynamic: license-file
